CalculatorMathHamza/Calculator.py
CalculatorMathHamza/__init__.py
CalculatorMathHamza-0.0.1.dist-info/METADATA
CalculatorMathHamza-0.0.1.dist-info/WHEEL
CalculatorMathHamza-0.0.1.dist-info/license.txt
CalculatorMathHamza-0.0.1.dist-info/top_level.txt
CalculatorMathHamza-0.0.1.dist-info/RECORD
